{
  "downloads": [
    {
      "date": "05/02/2021",
      "2.0.0": 50,
      "2.0.0-alpha1": 1104,
      "1.2.1": 7422,
      "1.2.0": 2791,
      "1.2.0-beta1": 1,
      "1.2.0-alpha1": 2,
      "1.1.0": 1692,
      "1.1.0-alpha2": 1,
      "1.1.0-alpha1": 45,
      "1.0.5": 428,
      "1.0.4": 1,
      "1.0.3": 2596,
      "1.0.2": 1,
      "1.0.1": 1,
      "1.0.0": 1,
      "1.0.0-beta1": 1,
      "1.0.0-alpha5": 1,
      "1.0.0-alpha4": 1,
      "1.0.0-alpha3": 1,
      "1.0.0-alpha2": 1,
      "1.0.0-alpha1": 1
    }
  ]
}
