{
  "downloads": [
    {
      "date": "08/02/2021",
      "22.0.0-beta1": 0,
      "22.0.0-alpha9": 0,
      "22.0.0-alpha8": 0,
      "22.0.0-alpha7": 0,
      "22.0.0-alpha6": 0,
      "22.0.0-alpha5": 0,
      "22.0.0-alpha4": 0,
      "22.0.0-alpha3": 0,
      "22.0.0-alpha2": 0,
      "22.0.0-alpha10": 0,
      "22.0.0-alpha1": 0,
      "21.0.3": 0,
      "21.0.2": 0,
      "21.0.1": 0,
      "21.0.0": 0,
      "21.0.0-rc1": 0,
      "21.0.0-beta2": 0,
      "21.0.0-beta1": 0,
      "21.0.0-alpha9": 0,
      "21.0.0-alpha8": 0,
      "21.0.0-alpha7": 0,
      "21.0.0-alpha6": 0,
      "21.0.0-alpha5": 0,
      "21.0.0-alpha4": 0,
      "21.0.0-alpha3": 0,
      "21.0.0-alpha2": 0,
      "21.0.0-alpha13": 0,
      "21.0.0-alpha12": 0,
      "21.0.0-alpha11": 0,
      "21.0.0-alpha10": 0,
      "21.0.0-alpha1": 0,
      "21.0.0-alpha0.b163d3a8c": 0,
      "21.0.0-alpha0.29f1db3de": 0,
      "20.0.5": 0,
      "20.0.4": 0,
      "20.0.3": 0,
      "20.0.2": 0,
      "20.0.1": 0,
      "20.0.0": 0,
      "20.0.0-rc1": 0,
      "20.0.0-beta2": 0,
      "20.0.0-beta1": 0,
      "20.0.0-alpha6": 0,
      "20.0.0-alpha5": 0,
      "20.0.0-alpha4": 0,
      "20.0.0-alpha3": 0,
      "20.0.0-alpha2": 0,
      "20.0.0-alpha1": 0,
      "5.0.0-alpha1": 0,
      "4.3.0": 9577,
      "4.3.0-beta1": 0,
      "4.3.0-alpha1": 1,
      "4.2.0": 1759,
      "4.2.0-alpha1": 39,
      "4.1.1": 3138,
      "4.1.0": 53,
      "4.1.0-beta2": 1,
      "4.1.0-beta1": 0,
      "4.1.0-alpha3": 0,
      "4.1.0-alpha2": 0
    },
    {
      "date": "15/02/2021",
      "22.0.0-beta1": 0,
      "22.0.0-alpha9": 0,
      "22.0.0-alpha8": 0,
      "22.0.0-alpha7": 0,
      "22.0.0-alpha6": 0,
      "22.0.0-alpha5": 0,
      "22.0.0-alpha4": 0,
      "22.0.0-alpha3": 0,
      "22.0.0-alpha2": 0,
      "22.0.0-alpha10": 0,
      "22.0.0-alpha1": 0,
      "21.0.3": 0,
      "21.0.2": 0,
      "21.0.1": 0,
      "21.0.0": 0,
      "21.0.0-rc1": 0,
      "21.0.0-beta2": 0,
      "21.0.0-beta1": 0,
      "21.0.0-alpha9": 0,
      "21.0.0-alpha8": 0,
      "21.0.0-alpha7": 0,
      "21.0.0-alpha6": 0,
      "21.0.0-alpha5": 0,
      "21.0.0-alpha4": 0,
      "21.0.0-alpha3": 0,
      "21.0.0-alpha2": 0,
      "21.0.0-alpha13": 0,
      "21.0.0-alpha12": 0,
      "21.0.0-alpha11": 0,
      "21.0.0-alpha10": 0,
      "21.0.0-alpha1": 0,
      "21.0.0-alpha0.b163d3a8c": 0,
      "21.0.0-alpha0.29f1db3de": 0,
      "20.0.5": 0,
      "20.0.4": 0,
      "20.0.3": 0,
      "20.0.2": 0,
      "20.0.1": 0,
      "20.0.0": 0,
      "20.0.0-rc1": 0,
      "20.0.0-beta2": 0,
      "20.0.0-beta1": 0,
      "20.0.0-alpha6": 0,
      "20.0.0-alpha5": 0,
      "20.0.0-alpha4": 0,
      "20.0.0-alpha3": 0,
      "20.0.0-alpha2": 0,
      "20.0.0-alpha1": 0,
      "5.0.0-alpha1": 6,
      "4.3.0": 8974,
      "4.3.0-beta1": 0,
      "4.3.0-alpha1": 0,
      "4.2.0": 1698,
      "4.2.0-alpha1": 33,
      "4.1.1": 3249,
      "4.1.0": 3,
      "4.1.0-beta2": 0,
      "4.1.0-beta1": 0,
      "4.1.0-alpha3": 0,
      "4.1.0-alpha2": 0
    },
    {
      "date": "22/02/2021",
      "22.0.0-beta1": 0,
      "22.0.0-alpha9": 0,
      "22.0.0-alpha8": 0,
      "22.0.0-alpha7": 0,
      "22.0.0-alpha6": 0,
      "22.0.0-alpha5": 0,
      "22.0.0-alpha4": 0,
      "22.0.0-alpha3": 0,
      "22.0.0-alpha2": 0,
      "22.0.0-alpha10": 0,
      "22.0.0-alpha1": 0,
      "21.0.3": 0,
      "21.0.2": 0,
      "21.0.1": 0,
      "21.0.0": 0,
      "21.0.0-rc1": 0,
      "21.0.0-beta2": 0,
      "21.0.0-beta1": 0,
      "21.0.0-alpha9": 0,
      "21.0.0-alpha8": 0,
      "21.0.0-alpha7": 0,
      "21.0.0-alpha6": 0,
      "21.0.0-alpha5": 0,
      "21.0.0-alpha4": 0,
      "21.0.0-alpha3": 0,
      "21.0.0-alpha2": 0,
      "21.0.0-alpha13": 0,
      "21.0.0-alpha12": 0,
      "21.0.0-alpha11": 0,
      "21.0.0-alpha10": 0,
      "21.0.0-alpha1": 0,
      "21.0.0-alpha0.b163d3a8c": 0,
      "21.0.0-alpha0.29f1db3de": 0,
      "20.0.5": 0,
      "20.0.4": 0,
      "20.0.3": 0,
      "20.0.2": 0,
      "20.0.1": 0,
      "20.0.0": 0,
      "20.0.0-rc1": 0,
      "20.0.0-beta2": 0,
      "20.0.0-beta1": 0,
      "20.0.0-alpha6": 0,
      "20.0.0-alpha5": 0,
      "20.0.0-alpha4": 0,
      "20.0.0-alpha3": 0,
      "20.0.0-alpha2": 0,
      "20.0.0-alpha1": 0,
      "5.0.0-alpha1": 2,
      "4.3.0": 9264,
      "4.3.0-beta1": 1,
      "4.3.0-alpha1": 1,
      "4.2.0": 1373,
      "4.2.0-alpha1": 38,
      "4.1.1": 3304,
      "4.1.0": 35,
      "4.1.0-beta2": 1,
      "4.1.0-beta1": 1,
      "4.1.0-alpha3": 1,
      "4.1.0-alpha2": 1
    },
    {
      "date": "01/03/2021",
      "22.0.0-beta1": 0,
      "22.0.0-alpha9": 0,
      "22.0.0-alpha8": 0,
      "22.0.0-alpha7": 0,
      "22.0.0-alpha6": 0,
      "22.0.0-alpha5": 0,
      "22.0.0-alpha4": 0,
      "22.0.0-alpha3": 0,
      "22.0.0-alpha2": 0,
      "22.0.0-alpha10": 0,
      "22.0.0-alpha1": 0,
      "21.0.3": 0,
      "21.0.2": 0,
      "21.0.1": 0,
      "21.0.0": 0,
      "21.0.0-rc1": 0,
      "21.0.0-beta2": 0,
      "21.0.0-beta1": 0,
      "21.0.0-alpha9": 0,
      "21.0.0-alpha8": 0,
      "21.0.0-alpha7": 0,
      "21.0.0-alpha6": 0,
      "21.0.0-alpha5": 0,
      "21.0.0-alpha4": 0,
      "21.0.0-alpha3": 0,
      "21.0.0-alpha2": 0,
      "21.0.0-alpha13": 0,
      "21.0.0-alpha12": 0,
      "21.0.0-alpha11": 0,
      "21.0.0-alpha10": 0,
      "21.0.0-alpha1": 0,
      "21.0.0-alpha0.b163d3a8c": 0,
      "21.0.0-alpha0.29f1db3de": 0,
      "20.0.5": 0,
      "20.0.4": 0,
      "20.0.3": 0,
      "20.0.2": 0,
      "20.0.1": 0,
      "20.0.0": 0,
      "20.0.0-rc1": 0,
      "20.0.0-beta2": 0,
      "20.0.0-beta1": 0,
      "20.0.0-alpha6": 0,
      "20.0.0-alpha5": 0,
      "20.0.0-alpha4": 0,
      "20.0.0-alpha3": 0,
      "20.0.0-alpha2": 0,
      "20.0.0-alpha1": 0,
      "5.0.0-alpha1": 0,
      "4.3.0": 9525,
      "4.3.0-beta1": 0,
      "4.3.0-alpha1": 0,
      "4.2.0": 1373,
      "4.2.0-alpha1": 41,
      "4.1.1": 2104,
      "4.1.0": 17,
      "4.1.0-beta2": 0,
      "4.1.0-beta1": 0,
      "4.1.0-alpha3": 0,
      "4.1.0-alpha2": 0
    },
    {
      "date": "08/03/2021",
      "22.0.0-beta1": 0,
      "22.0.0-alpha9": 0,
      "22.0.0-alpha8": 0,
      "22.0.0-alpha7": 0,
      "22.0.0-alpha6": 0,
      "22.0.0-alpha5": 0,
      "22.0.0-alpha4": 0,
      "22.0.0-alpha3": 0,
      "22.0.0-alpha2": 0,
      "22.0.0-alpha10": 0,
      "22.0.0-alpha1": 0,
      "21.0.3": 0,
      "21.0.2": 0,
      "21.0.1": 0,
      "21.0.0": 0,
      "21.0.0-rc1": 0,
      "21.0.0-beta2": 0,
      "21.0.0-beta1": 0,
      "21.0.0-alpha9": 0,
      "21.0.0-alpha8": 0,
      "21.0.0-alpha7": 0,
      "21.0.0-alpha6": 0,
      "21.0.0-alpha5": 0,
      "21.0.0-alpha4": 0,
      "21.0.0-alpha3": 0,
      "21.0.0-alpha2": 0,
      "21.0.0-alpha13": 0,
      "21.0.0-alpha12": 0,
      "21.0.0-alpha11": 0,
      "21.0.0-alpha10": 0,
      "21.0.0-alpha1": 0,
      "21.0.0-alpha0.b163d3a8c": 0,
      "21.0.0-alpha0.29f1db3de": 0,
      "20.0.5": 0,
      "20.0.4": 0,
      "20.0.3": 0,
      "20.0.2": 0,
      "20.0.1": 0,
      "20.0.0": 0,
      "20.0.0-rc1": 0,
      "20.0.0-beta2": 0,
      "20.0.0-beta1": 0,
      "20.0.0-alpha6": 0,
      "20.0.0-alpha5": 0,
      "20.0.0-alpha4": 0,
      "20.0.0-alpha3": 0,
      "20.0.0-alpha2": 0,
      "20.0.0-alpha1": 0,
      "5.0.0-alpha1": 0,
      "4.3.0": 9755,
      "4.3.0-beta1": 0,
      "4.3.0-alpha1": 3,
      "4.2.0": 1271,
      "4.2.0-alpha1": 36,
      "4.1.1": 2090,
      "4.1.0": 31,
      "4.1.0-beta2": 0,
      "4.1.0-beta1": 0,
      "4.1.0-alpha3": 0,
      "4.1.0-alpha2": 0
    },
    {
      "date": "15/03/2021",
      "22.0.0-beta1": 0,
      "22.0.0-alpha9": 0,
      "22.0.0-alpha8": 0,
      "22.0.0-alpha7": 0,
      "22.0.0-alpha6": 0,
      "22.0.0-alpha5": 0,
      "22.0.0-alpha4": 0,
      "22.0.0-alpha3": 0,
      "22.0.0-alpha2": 0,
      "22.0.0-alpha10": 0,
      "22.0.0-alpha1": 0,
      "21.0.3": 0,
      "21.0.2": 0,
      "21.0.1": 0,
      "21.0.0": 0,
      "21.0.0-rc1": 0,
      "21.0.0-beta2": 0,
      "21.0.0-beta1": 0,
      "21.0.0-alpha9": 0,
      "21.0.0-alpha8": 0,
      "21.0.0-alpha7": 0,
      "21.0.0-alpha6": 0,
      "21.0.0-alpha5": 0,
      "21.0.0-alpha4": 0,
      "21.0.0-alpha3": 0,
      "21.0.0-alpha2": 0,
      "21.0.0-alpha13": 0,
      "21.0.0-alpha12": 0,
      "21.0.0-alpha11": 0,
      "21.0.0-alpha10": 0,
      "21.0.0-alpha1": 0,
      "21.0.0-alpha0.b163d3a8c": 0,
      "21.0.0-alpha0.29f1db3de": 0,
      "20.0.5": 0,
      "20.0.4": 0,
      "20.0.3": 0,
      "20.0.2": 0,
      "20.0.1": 0,
      "20.0.0": 0,
      "20.0.0-rc1": 0,
      "20.0.0-beta2": 0,
      "20.0.0-beta1": 0,
      "20.0.0-alpha6": 0,
      "20.0.0-alpha5": 0,
      "20.0.0-alpha4": 0,
      "20.0.0-alpha3": 0,
      "20.0.0-alpha2": 0,
      "20.0.0-alpha1": 26,
      "5.0.0-alpha1": 1,
      "4.3.0": 9433,
      "4.3.0-beta1": 1,
      "4.3.0-alpha1": 2,
      "4.2.0": 1275,
      "4.2.0-alpha1": 39,
      "4.1.1": 1999,
      "4.1.0": 29,
      "4.1.0-beta2": 1,
      "4.1.0-beta1": 2,
      "4.1.0-alpha3": 2,
      "4.1.0-alpha2": 2
    },
    {
      "date": "22/03/2021",
      "22.0.0-beta1": 0,
      "22.0.0-alpha9": 0,
      "22.0.0-alpha8": 0,
      "22.0.0-alpha7": 0,
      "22.0.0-alpha6": 0,
      "22.0.0-alpha5": 0,
      "22.0.0-alpha4": 0,
      "22.0.0-alpha3": 0,
      "22.0.0-alpha2": 0,
      "22.0.0-alpha10": 0,
      "22.0.0-alpha1": 0,
      "21.0.3": 0,
      "21.0.2": 0,
      "21.0.1": 0,
      "21.0.0": 0,
      "21.0.0-rc1": 0,
      "21.0.0-beta2": 0,
      "21.0.0-beta1": 0,
      "21.0.0-alpha9": 0,
      "21.0.0-alpha8": 0,
      "21.0.0-alpha7": 0,
      "21.0.0-alpha6": 0,
      "21.0.0-alpha5": 0,
      "21.0.0-alpha4": 0,
      "21.0.0-alpha3": 0,
      "21.0.0-alpha2": 0,
      "21.0.0-alpha13": 0,
      "21.0.0-alpha12": 0,
      "21.0.0-alpha11": 0,
      "21.0.0-alpha10": 0,
      "21.0.0-alpha1": 0,
      "21.0.0-alpha0.b163d3a8c": 0,
      "21.0.0-alpha0.29f1db3de": 0,
      "20.0.5": 0,
      "20.0.4": 0,
      "20.0.3": 0,
      "20.0.2": 0,
      "20.0.1": 0,
      "20.0.0": 0,
      "20.0.0-rc1": 0,
      "20.0.0-beta2": 0,
      "20.0.0-beta1": 0,
      "20.0.0-alpha6": 0,
      "20.0.0-alpha5": 0,
      "20.0.0-alpha4": 0,
      "20.0.0-alpha3": 0,
      "20.0.0-alpha2": 0,
      "20.0.0-alpha1": 43,
      "5.0.0-alpha1": 8,
      "4.3.0": 9824,
      "4.3.0-beta1": 6,
      "4.3.0-alpha1": 6,
      "4.2.0": 1207,
      "4.2.0-alpha1": 40,
      "4.1.1": 2093,
      "4.1.0": 26,
      "4.1.0-beta2": 6,
      "4.1.0-beta1": 4,
      "4.1.0-alpha3": 5,
      "4.1.0-alpha2": 4
    },
    {
      "date": "29/03/2021",
      "22.0.0-beta1": 0,
      "22.0.0-alpha9": 0,
      "22.0.0-alpha8": 0,
      "22.0.0-alpha7": 0,
      "22.0.0-alpha6": 0,
      "22.0.0-alpha5": 0,
      "22.0.0-alpha4": 0,
      "22.0.0-alpha3": 0,
      "22.0.0-alpha2": 0,
      "22.0.0-alpha10": 0,
      "22.0.0-alpha1": 0,
      "21.0.3": 0,
      "21.0.2": 0,
      "21.0.1": 0,
      "21.0.0": 0,
      "21.0.0-rc1": 0,
      "21.0.0-beta2": 0,
      "21.0.0-beta1": 0,
      "21.0.0-alpha9": 0,
      "21.0.0-alpha8": 0,
      "21.0.0-alpha7": 0,
      "21.0.0-alpha6": 0,
      "21.0.0-alpha5": 0,
      "21.0.0-alpha4": 0,
      "21.0.0-alpha3": 0,
      "21.0.0-alpha2": 0,
      "21.0.0-alpha13": 0,
      "21.0.0-alpha12": 0,
      "21.0.0-alpha11": 0,
      "21.0.0-alpha10": 0,
      "21.0.0-alpha1": 0,
      "21.0.0-alpha0.b163d3a8c": 0,
      "21.0.0-alpha0.29f1db3de": 0,
      "20.0.5": 0,
      "20.0.4": 0,
      "20.0.3": 0,
      "20.0.2": 0,
      "20.0.1": 0,
      "20.0.0": 0,
      "20.0.0-rc1": 0,
      "20.0.0-beta2": 0,
      "20.0.0-beta1": 0,
      "20.0.0-alpha6": 0,
      "20.0.0-alpha5": 0,
      "20.0.0-alpha4": 0,
      "20.0.0-alpha3": 0,
      "20.0.0-alpha2": 77,
      "20.0.0-alpha1": 66,
      "5.0.0-alpha1": 4,
      "4.3.0": 10621,
      "4.3.0-beta1": 2,
      "4.3.0-alpha1": 4,
      "4.2.0": 1347,
      "4.2.0-alpha1": 32,
      "4.1.1": 2711,
      "4.1.0": 13,
      "4.1.0-beta2": 4,
      "4.1.0-beta1": 5,
      "4.1.0-alpha3": 4,
      "4.1.0-alpha2": 4
    },
    {
      "date": "05/04/2021",
      "22.0.0-beta1": 0,
      "22.0.0-alpha9": 0,
      "22.0.0-alpha8": 0,
      "22.0.0-alpha7": 0,
      "22.0.0-alpha6": 0,
      "22.0.0-alpha5": 0,
      "22.0.0-alpha4": 0,
      "22.0.0-alpha3": 0,
      "22.0.0-alpha2": 0,
      "22.0.0-alpha10": 0,
      "22.0.0-alpha1": 0,
      "21.0.3": 0,
      "21.0.2": 0,
      "21.0.1": 0,
      "21.0.0": 0,
      "21.0.0-rc1": 0,
      "21.0.0-beta2": 0,
      "21.0.0-beta1": 0,
      "21.0.0-alpha9": 0,
      "21.0.0-alpha8": 0,
      "21.0.0-alpha7": 0,
      "21.0.0-alpha6": 0,
      "21.0.0-alpha5": 0,
      "21.0.0-alpha4": 0,
      "21.0.0-alpha3": 0,
      "21.0.0-alpha2": 0,
      "21.0.0-alpha13": 0,
      "21.0.0-alpha12": 0,
      "21.0.0-alpha11": 0,
      "21.0.0-alpha10": 0,
      "21.0.0-alpha1": 0,
      "21.0.0-alpha0.b163d3a8c": 0,
      "21.0.0-alpha0.29f1db3de": 0,
      "20.0.5": 0,
      "20.0.4": 0,
      "20.0.3": 0,
      "20.0.2": 0,
      "20.0.1": 0,
      "20.0.0": 0,
      "20.0.0-rc1": 0,
      "20.0.0-beta2": 0,
      "20.0.0-beta1": 0,
      "20.0.0-alpha6": 0,
      "20.0.0-alpha5": 0,
      "20.0.0-alpha4": 0,
      "20.0.0-alpha3": 169,
      "20.0.0-alpha2": 242,
      "20.0.0-alpha1": 10,
      "5.0.0-alpha1": 0,
      "4.3.0": 7884,
      "4.3.0-beta1": 0,
      "4.3.0-alpha1": 2,
      "4.2.0": 1571,
      "4.2.0-alpha1": 33,
      "4.1.1": 2392,
      "4.1.0": 12,
      "4.1.0-beta2": 0,
      "4.1.0-beta1": 0,
      "4.1.0-alpha3": 0,
      "4.1.0-alpha2": 0
    },
    {
      "date": "12/04/2021",
      "22.0.0-beta1": 0,
      "22.0.0-alpha9": 0,
      "22.0.0-alpha8": 0,
      "22.0.0-alpha7": 0,
      "22.0.0-alpha6": 0,
      "22.0.0-alpha5": 0,
      "22.0.0-alpha4": 0,
      "22.0.0-alpha3": 0,
      "22.0.0-alpha2": 0,
      "22.0.0-alpha10": 0,
      "22.0.0-alpha1": 0,
      "21.0.3": 0,
      "21.0.2": 0,
      "21.0.1": 0,
      "21.0.0": 0,
      "21.0.0-rc1": 0,
      "21.0.0-beta2": 0,
      "21.0.0-beta1": 0,
      "21.0.0-alpha9": 0,
      "21.0.0-alpha8": 0,
      "21.0.0-alpha7": 0,
      "21.0.0-alpha6": 0,
      "21.0.0-alpha5": 0,
      "21.0.0-alpha4": 0,
      "21.0.0-alpha3": 0,
      "21.0.0-alpha2": 0,
      "21.0.0-alpha13": 0,
      "21.0.0-alpha12": 0,
      "21.0.0-alpha11": 0,
      "21.0.0-alpha10": 0,
      "21.0.0-alpha1": 0,
      "21.0.0-alpha0.b163d3a8c": 0,
      "21.0.0-alpha0.29f1db3de": 0,
      "20.0.5": 0,
      "20.0.4": 0,
      "20.0.3": 0,
      "20.0.2": 0,
      "20.0.1": 0,
      "20.0.0": 0,
      "20.0.0-rc1": 0,
      "20.0.0-beta2": 0,
      "20.0.0-beta1": 0,
      "20.0.0-alpha6": 0,
      "20.0.0-alpha5": 0,
      "20.0.0-alpha4": 28,
      "20.0.0-alpha3": 202,
      "20.0.0-alpha2": 236,
      "20.0.0-alpha1": 3,
      "5.0.0-alpha1": 2,
      "4.3.0": 7991,
      "4.3.0-beta1": 2,
      "4.3.0-alpha1": 2,
      "4.2.0": 1291,
      "4.2.0-alpha1": 36,
      "4.1.1": 2115,
      "4.1.0": 17,
      "4.1.0-beta2": 1,
      "4.1.0-beta1": 1,
      "4.1.0-alpha3": 1,
      "4.1.0-alpha2": 1
    },
    {
      "date": "19/04/2021",
      "22.0.0-beta1": 0,
      "22.0.0-alpha9": 0,
      "22.0.0-alpha8": 0,
      "22.0.0-alpha7": 0,
      "22.0.0-alpha6": 0,
      "22.0.0-alpha5": 0,
      "22.0.0-alpha4": 0,
      "22.0.0-alpha3": 0,
      "22.0.0-alpha2": 0,
      "22.0.0-alpha10": 0,
      "22.0.0-alpha1": 0,
      "21.0.3": 0,
      "21.0.2": 0,
      "21.0.1": 0,
      "21.0.0": 0,
      "21.0.0-rc1": 0,
      "21.0.0-beta2": 0,
      "21.0.0-beta1": 0,
      "21.0.0-alpha9": 0,
      "21.0.0-alpha8": 0,
      "21.0.0-alpha7": 0,
      "21.0.0-alpha6": 0,
      "21.0.0-alpha5": 0,
      "21.0.0-alpha4": 0,
      "21.0.0-alpha3": 0,
      "21.0.0-alpha2": 0,
      "21.0.0-alpha13": 0,
      "21.0.0-alpha12": 0,
      "21.0.0-alpha11": 0,
      "21.0.0-alpha10": 0,
      "21.0.0-alpha1": 0,
      "21.0.0-alpha0.b163d3a8c": 0,
      "21.0.0-alpha0.29f1db3de": 0,
      "20.0.5": 0,
      "20.0.4": 0,
      "20.0.3": 0,
      "20.0.2": 0,
      "20.0.1": 0,
      "20.0.0": 0,
      "20.0.0-rc1": 0,
      "20.0.0-beta2": 0,
      "20.0.0-beta1": 0,
      "20.0.0-alpha6": 0,
      "20.0.0-alpha5": 0,
      "20.0.0-alpha4": 379,
      "20.0.0-alpha3": 177,
      "20.0.0-alpha2": 145,
      "20.0.0-alpha1": 3,
      "5.0.0-alpha1": 3,
      "4.3.0": 9608,
      "4.3.0-beta1": 2,
      "4.3.0-alpha1": 1,
      "4.2.0": 1295,
      "4.2.0-alpha1": 30,
      "4.1.1": 2360,
      "4.1.0": 11,
      "4.1.0-beta2": 1,
      "4.1.0-beta1": 1,
      "4.1.0-alpha3": 1,
      "4.1.0-alpha2": 1
    },
    {
      "date": "26/04/2021",
      "22.0.0-beta1": 0,
      "22.0.0-alpha9": 0,
      "22.0.0-alpha8": 0,
      "22.0.0-alpha7": 0,
      "22.0.0-alpha6": 0,
      "22.0.0-alpha5": 0,
      "22.0.0-alpha4": 0,
      "22.0.0-alpha3": 0,
      "22.0.0-alpha2": 0,
      "22.0.0-alpha10": 0,
      "22.0.0-alpha1": 0,
      "21.0.3": 0,
      "21.0.2": 0,
      "21.0.1": 0,
      "21.0.0": 0,
      "21.0.0-rc1": 0,
      "21.0.0-beta2": 0,
      "21.0.0-beta1": 0,
      "21.0.0-alpha9": 0,
      "21.0.0-alpha8": 0,
      "21.0.0-alpha7": 0,
      "21.0.0-alpha6": 0,
      "21.0.0-alpha5": 0,
      "21.0.0-alpha4": 0,
      "21.0.0-alpha3": 0,
      "21.0.0-alpha2": 0,
      "21.0.0-alpha13": 0,
      "21.0.0-alpha12": 0,
      "21.0.0-alpha11": 0,
      "21.0.0-alpha10": 0,
      "21.0.0-alpha1": 0,
      "21.0.0-alpha0.b163d3a8c": 0,
      "21.0.0-alpha0.29f1db3de": 0,
      "20.0.5": 0,
      "20.0.4": 0,
      "20.0.3": 0,
      "20.0.2": 0,
      "20.0.1": 0,
      "20.0.0": 0,
      "20.0.0-rc1": 0,
      "20.0.0-beta2": 0,
      "20.0.0-beta1": 0,
      "20.0.0-alpha6": 0,
      "20.0.0-alpha5": 61,
      "20.0.0-alpha4": 258,
      "20.0.0-alpha3": 14,
      "20.0.0-alpha2": 5,
      "20.0.0-alpha1": 1,
      "5.0.0-alpha1": 0,
      "4.3.0": 9813,
      "4.3.0-beta1": 0,
      "4.3.0-alpha1": 4,
      "4.2.0": 1336,
      "4.2.0-alpha1": 37,
      "4.1.1": 2603,
      "4.1.0": 7,
      "4.1.0-beta2": 2,
      "4.1.0-beta1": 0,
      "4.1.0-alpha3": 0,
      "4.1.0-alpha2": 0
    },
    {
      "date": "03/05/2021",
      "22.0.0-beta1": 0,
      "22.0.0-alpha9": 0,
      "22.0.0-alpha8": 0,
      "22.0.0-alpha7": 0,
      "22.0.0-alpha6": 0,
      "22.0.0-alpha5": 0,
      "22.0.0-alpha4": 0,
      "22.0.0-alpha3": 0,
      "22.0.0-alpha2": 0,
      "22.0.0-alpha10": 0,
      "22.0.0-alpha1": 0,
      "21.0.3": 0,
      "21.0.2": 0,
      "21.0.1": 0,
      "21.0.0": 0,
      "21.0.0-rc1": 0,
      "21.0.0-beta2": 0,
      "21.0.0-beta1": 0,
      "21.0.0-alpha9": 0,
      "21.0.0-alpha8": 0,
      "21.0.0-alpha7": 0,
      "21.0.0-alpha6": 0,
      "21.0.0-alpha5": 0,
      "21.0.0-alpha4": 0,
      "21.0.0-alpha3": 0,
      "21.0.0-alpha2": 0,
      "21.0.0-alpha13": 0,
      "21.0.0-alpha12": 0,
      "21.0.0-alpha11": 0,
      "21.0.0-alpha10": 0,
      "21.0.0-alpha1": 0,
      "21.0.0-alpha0.b163d3a8c": 0,
      "21.0.0-alpha0.29f1db3de": 0,
      "20.0.5": 0,
      "20.0.4": 0,
      "20.0.3": 0,
      "20.0.2": 0,
      "20.0.1": 0,
      "20.0.0": 0,
      "20.0.0-rc1": 0,
      "20.0.0-beta2": 0,
      "20.0.0-beta1": 0,
      "20.0.0-alpha6": 57,
      "20.0.0-alpha5": 292,
      "20.0.0-alpha4": 229,
      "20.0.0-alpha3": 2,
      "20.0.0-alpha2": 2,
      "20.0.0-alpha1": 2,
      "5.0.0-alpha1": 2,
      "4.3.0": 9458,
      "4.3.0-beta1": 3,
      "4.3.0-alpha1": 3,
      "4.2.0": 1123,
      "4.2.0-alpha1": 39,
      "4.1.1": 2301,
      "4.1.0": 4,
      "4.1.0-beta2": 0,
      "4.1.0-beta1": 1,
      "4.1.0-alpha3": 0,
      "4.1.0-alpha2": 0
    },
    {
      "date": "10/05/2021",
      "22.0.0-beta1": 0,
      "22.0.0-alpha9": 0,
      "22.0.0-alpha8": 0,
      "22.0.0-alpha7": 0,
      "22.0.0-alpha6": 0,
      "22.0.0-alpha5": 0,
      "22.0.0-alpha4": 0,
      "22.0.0-alpha3": 0,
      "22.0.0-alpha2": 0,
      "22.0.0-alpha10": 0,
      "22.0.0-alpha1": 0,
      "21.0.3": 0,
      "21.0.2": 0,
      "21.0.1": 0,
      "21.0.0": 0,
      "21.0.0-rc1": 0,
      "21.0.0-beta2": 0,
      "21.0.0-beta1": 0,
      "21.0.0-alpha9": 0,
      "21.0.0-alpha8": 0,
      "21.0.0-alpha7": 0,
      "21.0.0-alpha6": 0,
      "21.0.0-alpha5": 0,
      "21.0.0-alpha4": 0,
      "21.0.0-alpha3": 0,
      "21.0.0-alpha2": 0,
      "21.0.0-alpha13": 0,
      "21.0.0-alpha12": 0,
      "21.0.0-alpha11": 0,
      "21.0.0-alpha10": 0,
      "21.0.0-alpha1": 0,
      "21.0.0-alpha0.b163d3a8c": 27,
      "21.0.0-alpha0.29f1db3de": 27,
      "20.0.5": 0,
      "20.0.4": 0,
      "20.0.3": 0,
      "20.0.2": 0,
      "20.0.1": 0,
      "20.0.0": 0,
      "20.0.0-rc1": 0,
      "20.0.0-beta2": 0,
      "20.0.0-beta1": 450,
      "20.0.0-alpha6": 26,
      "20.0.0-alpha5": 316,
      "20.0.0-alpha4": 15,
      "20.0.0-alpha3": 5,
      "20.0.0-alpha2": 1,
      "20.0.0-alpha1": 1,
      "5.0.0-alpha1": 1,
      "4.3.0": 9382,
      "4.3.0-beta1": 0,
      "4.3.0-alpha1": 0,
      "4.2.0": 1121,
      "4.2.0-alpha1": 40,
      "4.1.1": 1816,
      "4.1.0": 10,
      "4.1.0-beta2": 0,
      "4.1.0-beta1": 0,
      "4.1.0-alpha3": 0,
      "4.1.0-alpha2": 1
    },
    {
      "date": "17/05/2021",
      "22.0.0-beta1": 0,
      "22.0.0-alpha9": 0,
      "22.0.0-alpha8": 0,
      "22.0.0-alpha7": 0,
      "22.0.0-alpha6": 0,
      "22.0.0-alpha5": 0,
      "22.0.0-alpha4": 0,
      "22.0.0-alpha3": 0,
      "22.0.0-alpha2": 0,
      "22.0.0-alpha10": 0,
      "22.0.0-alpha1": 0,
      "21.0.3": 0,
      "21.0.2": 0,
      "21.0.1": 0,
      "21.0.0": 0,
      "21.0.0-rc1": 0,
      "21.0.0-beta2": 0,
      "21.0.0-beta1": 0,
      "21.0.0-alpha9": 0,
      "21.0.0-alpha8": 0,
      "21.0.0-alpha7": 0,
      "21.0.0-alpha6": 0,
      "21.0.0-alpha5": 0,
      "21.0.0-alpha4": 0,
      "21.0.0-alpha3": 0,
      "21.0.0-alpha2": 0,
      "21.0.0-alpha13": 0,
      "21.0.0-alpha12": 0,
      "21.0.0-alpha11": 0,
      "21.0.0-alpha10": 0,
      "21.0.0-alpha1": 89,
      "21.0.0-alpha0.b163d3a8c": 24,
      "21.0.0-alpha0.29f1db3de": 4,
      "20.0.5": 0,
      "20.0.4": 0,
      "20.0.3": 0,
      "20.0.2": 0,
      "20.0.1": 0,
      "20.0.0": 0,
      "20.0.0-rc1": 0,
      "20.0.0-beta2": 0,
      "20.0.0-beta1": 372,
      "20.0.0-alpha6": 5,
      "20.0.0-alpha5": 13,
      "20.0.0-alpha4": 6,
      "20.0.0-alpha3": 66,
      "20.0.0-alpha2": 2,
      "20.0.0-alpha1": 3,
      "5.0.0-alpha1": 2,
      "4.3.0": 8953,
      "4.3.0-beta1": 2,
      "4.3.0-alpha1": 2,
      "4.2.0": 1209,
      "4.2.0-alpha1": 51,
      "4.1.1": 2309,
      "4.1.0": 26,
      "4.1.0-beta2": 2,
      "4.1.0-beta1": 2,
      "4.1.0-alpha3": 2,
      "4.1.0-alpha2": 2
    },
    {
      "date": "24/05/2021",
      "22.0.0-beta1": 0,
      "22.0.0-alpha9": 0,
      "22.0.0-alpha8": 0,
      "22.0.0-alpha7": 0,
      "22.0.0-alpha6": 0,
      "22.0.0-alpha5": 0,
      "22.0.0-alpha4": 0,
      "22.0.0-alpha3": 0,
      "22.0.0-alpha2": 0,
      "22.0.0-alpha10": 0,
      "22.0.0-alpha1": 0,
      "21.0.3": 0,
      "21.0.2": 0,
      "21.0.1": 0,
      "21.0.0": 0,
      "21.0.0-rc1": 0,
      "21.0.0-beta2": 0,
      "21.0.0-beta1": 0,
      "21.0.0-alpha9": 0,
      "21.0.0-alpha8": 0,
      "21.0.0-alpha7": 0,
      "21.0.0-alpha6": 0,
      "21.0.0-alpha5": 0,
      "21.0.0-alpha4": 0,
      "21.0.0-alpha3": 0,
      "21.0.0-alpha2": 319,
      "21.0.0-alpha13": 0,
      "21.0.0-alpha12": 0,
      "21.0.0-alpha11": 0,
      "21.0.0-alpha10": 0,
      "21.0.0-alpha1": 54,
      "21.0.0-alpha0.b163d3a8c": 1,
      "21.0.0-alpha0.29f1db3de": 1,
      "20.0.5": 0,
      "20.0.4": 0,
      "20.0.3": 0,
      "20.0.2": 0,
      "20.0.1": 0,
      "20.0.0": 0,
      "20.0.0-rc1": 0,
      "20.0.0-beta2": 125,
      "20.0.0-beta1": 170,
      "20.0.0-alpha6": 5,
      "20.0.0-alpha5": 10,
      "20.0.0-alpha4": 40,
      "20.0.0-alpha3": 75,
      "20.0.0-alpha2": 6,
      "20.0.0-alpha1": 1,
      "5.0.0-alpha1": 1,
      "4.3.0": 8624,
      "4.3.0-beta1": 1,
      "4.3.0-alpha1": 1,
      "4.2.0": 1015,
      "4.2.0-alpha1": 35,
      "4.1.1": 1857,
      "4.1.0": 6,
      "4.1.0-beta2": 1,
      "4.1.0-beta1": 1,
      "4.1.0-alpha3": 2,
      "4.1.0-alpha2": 1
    },
    {
      "date": "31/05/2021",
      "22.0.0-beta1": 0,
      "22.0.0-alpha9": 0,
      "22.0.0-alpha8": 0,
      "22.0.0-alpha7": 0,
      "22.0.0-alpha6": 0,
      "22.0.0-alpha5": 0,
      "22.0.0-alpha4": 0,
      "22.0.0-alpha3": 0,
      "22.0.0-alpha2": 0,
      "22.0.0-alpha10": 0,
      "22.0.0-alpha1": 0,
      "21.0.3": 0,
      "21.0.2": 0,
      "21.0.1": 0,
      "21.0.0": 0,
      "21.0.0-rc1": 0,
      "21.0.0-beta2": 0,
      "21.0.0-beta1": 0,
      "21.0.0-alpha9": 0,
      "21.0.0-alpha8": 0,
      "21.0.0-alpha7": 0,
      "21.0.0-alpha6": 0,
      "21.0.0-alpha5": 0,
      "21.0.0-alpha4": 0,
      "21.0.0-alpha3": 0,
      "21.0.0-alpha2": 380,
      "21.0.0-alpha13": 0,
      "21.0.0-alpha12": 0,
      "21.0.0-alpha11": 0,
      "21.0.0-alpha10": 0,
      "21.0.0-alpha1": 3,
      "21.0.0-alpha0.b163d3a8c": 2,
      "21.0.0-alpha0.29f1db3de": 2,
      "20.0.5": 0,
      "20.0.4": 0,
      "20.0.3": 0,
      "20.0.2": 0,
      "20.0.1": 0,
      "20.0.0": 0,
      "20.0.0-rc1": 157,
      "20.0.0-beta2": 41,
      "20.0.0-beta1": 91,
      "20.0.0-alpha6": 2,
      "20.0.0-alpha5": 2,
      "20.0.0-alpha4": 15,
      "20.0.0-alpha3": 21,
      "20.0.0-alpha2": 3,
      "20.0.0-alpha1": 1,
      "5.0.0-alpha1": 2,
      "4.3.0": 9777,
      "4.3.0-beta1": 1,
      "4.3.0-alpha1": 1,
      "4.2.0": 1254,
      "4.2.0-alpha1": 39,
      "4.1.1": 2238,
      "4.1.0": 9,
      "4.1.0-beta2": 1,
      "4.1.0-beta1": 1,
      "4.1.0-alpha3": 1,
      "4.1.0-alpha2": 2
    },
    {
      "date": "07/06/2021",
      "22.0.0-beta1": 0,
      "22.0.0-alpha9": 0,
      "22.0.0-alpha8": 0,
      "22.0.0-alpha7": 0,
      "22.0.0-alpha6": 0,
      "22.0.0-alpha5": 0,
      "22.0.0-alpha4": 0,
      "22.0.0-alpha3": 0,
      "22.0.0-alpha2": 0,
      "22.0.0-alpha10": 0,
      "22.0.0-alpha1": 0,
      "21.0.3": 0,
      "21.0.2": 0,
      "21.0.1": 0,
      "21.0.0": 0,
      "21.0.0-rc1": 0,
      "21.0.0-beta2": 0,
      "21.0.0-beta1": 0,
      "21.0.0-alpha9": 0,
      "21.0.0-alpha8": 0,
      "21.0.0-alpha7": 0,
      "21.0.0-alpha6": 0,
      "21.0.0-alpha5": 305,
      "21.0.0-alpha4": 30,
      "21.0.0-alpha3": 123,
      "21.0.0-alpha2": 590,
      "21.0.0-alpha13": 0,
      "21.0.0-alpha12": 0,
      "21.0.0-alpha11": 0,
      "21.0.0-alpha10": 0,
      "21.0.0-alpha1": 3,
      "21.0.0-alpha0.b163d3a8c": 3,
      "21.0.0-alpha0.29f1db3de": 3,
      "20.0.5": 0,
      "20.0.4": 0,
      "20.0.3": 0,
      "20.0.2": 0,
      "20.0.1": 0,
      "20.0.0": 826,
      "20.0.0-rc1": 29,
      "20.0.0-beta2": 4,
      "20.0.0-beta1": 7,
      "20.0.0-alpha6": 1,
      "20.0.0-alpha5": 1,
      "20.0.0-alpha4": 22,
      "20.0.0-alpha3": 28,
      "20.0.0-alpha2": 1,
      "20.0.0-alpha1": 1,
      "5.0.0-alpha1": 1,
      "4.3.0": 9226,
      "4.3.0-beta1": 1,
      "4.3.0-alpha1": 2,
      "4.2.0": 1094,
      "4.2.0-alpha1": 38,
      "4.1.1": 2140,
      "4.1.0": 4,
      "4.1.0-beta2": 1,
      "4.1.0-beta1": 1,
      "4.1.0-alpha3": 1,
      "4.1.0-alpha2": 1
    },
    {
      "date": "14/06/2021",
      "22.0.0-beta1": 0,
      "22.0.0-alpha9": 0,
      "22.0.0-alpha8": 0,
      "22.0.0-alpha7": 0,
      "22.0.0-alpha6": 0,
      "22.0.0-alpha5": 0,
      "22.0.0-alpha4": 0,
      "22.0.0-alpha3": 0,
      "22.0.0-alpha2": 0,
      "22.0.0-alpha10": 0,
      "22.0.0-alpha1": 0,
      "21.0.3": 0,
      "21.0.2": 0,
      "21.0.1": 0,
      "21.0.0": 0,
      "21.0.0-rc1": 0,
      "21.0.0-beta2": 0,
      "21.0.0-beta1": 0,
      "21.0.0-alpha9": 0,
      "21.0.0-alpha8": 0,
      "21.0.0-alpha7": 0,
      "21.0.0-alpha6": 315,
      "21.0.0-alpha5": 541,
      "21.0.0-alpha4": 1,
      "21.0.0-alpha3": 9,
      "21.0.0-alpha2": 119,
      "21.0.0-alpha13": 0,
      "21.0.0-alpha12": 0,
      "21.0.0-alpha11": 0,
      "21.0.0-alpha10": 0,
      "21.0.0-alpha1": 1,
      "21.0.0-alpha0.b163d3a8c": 1,
      "21.0.0-alpha0.29f1db3de": 1,
      "20.0.5": 0,
      "20.0.4": 0,
      "20.0.3": 0,
      "20.0.2": 0,
      "20.0.1": 0,
      "20.0.0": 1018,
      "20.0.0-rc1": 2,
      "20.0.0-beta2": 1,
      "20.0.0-beta1": 3,
      "20.0.0-alpha6": 1,
      "20.0.0-alpha5": 1,
      "20.0.0-alpha4": 1,
      "20.0.0-alpha3": 21,
      "20.0.0-alpha2": 1,
      "20.0.0-alpha1": 1,
      "5.0.0-alpha1": 1,
      "4.3.0": 9739,
      "4.3.0-beta1": 1,
      "4.3.0-alpha1": 1,
      "4.2.0": 1092,
      "4.2.0-alpha1": 40,
      "4.1.1": 2233,
      "4.1.0": 7,
      "4.1.0-beta2": 1,
      "4.1.0-beta1": 1,
      "4.1.0-alpha3": 1,
      "4.1.0-alpha2": 1
    },
    {
      "date": "21/06/2021",
      "22.0.0-beta1": 0,
      "22.0.0-alpha9": 0,
      "22.0.0-alpha8": 0,
      "22.0.0-alpha7": 0,
      "22.0.0-alpha6": 0,
      "22.0.0-alpha5": 0,
      "22.0.0-alpha4": 0,
      "22.0.0-alpha3": 0,
      "22.0.0-alpha2": 0,
      "22.0.0-alpha10": 0,
      "22.0.0-alpha1": 0,
      "21.0.3": 0,
      "21.0.2": 0,
      "21.0.1": 0,
      "21.0.0": 0,
      "21.0.0-rc1": 0,
      "21.0.0-beta2": 0,
      "21.0.0-beta1": 0,
      "21.0.0-alpha9": 0,
      "21.0.0-alpha8": 110,
      "21.0.0-alpha7": 31,
      "21.0.0-alpha6": 762,
      "21.0.0-alpha5": 23,
      "21.0.0-alpha4": 0,
      "21.0.0-alpha3": 3,
      "21.0.0-alpha2": 8,
      "21.0.0-alpha13": 0,
      "21.0.0-alpha12": 0,
      "21.0.0-alpha11": 0,
      "21.0.0-alpha10": 0,
      "21.0.0-alpha1": 0,
      "21.0.0-alpha0.b163d3a8c": 0,
      "21.0.0-alpha0.29f1db3de": 0,
      "20.0.5": 0,
      "20.0.4": 0,
      "20.0.3": 0,
      "20.0.2": 0,
      "20.0.1": 0,
      "20.0.0": 1009,
      "20.0.0-rc1": 0,
      "20.0.0-beta2": 0,
      "20.0.0-beta1": 4,
      "20.0.0-alpha6": 0,
      "20.0.0-alpha5": 0,
      "20.0.0-alpha4": 9,
      "20.0.0-alpha3": 16,
      "20.0.0-alpha2": 0,
      "20.0.0-alpha1": 0,
      "5.0.0-alpha1": 0,
      "4.3.0": 9703,
      "4.3.0-beta1": 0,
      "4.3.0-alpha1": 0,
      "4.2.0": 1147,
      "4.2.0-alpha1": 41,
      "4.1.1": 2060,
      "4.1.0": 4,
      "4.1.0-beta2": 0,
      "4.1.0-beta1": 0,
      "4.1.0-alpha3": 0,
      "4.1.0-alpha2": 0
    },
    {
      "date": "28/06/2021",
      "22.0.0-beta1": 0,
      "22.0.0-alpha9": 0,
      "22.0.0-alpha8": 0,
      "22.0.0-alpha7": 0,
      "22.0.0-alpha6": 0,
      "22.0.0-alpha5": 0,
      "22.0.0-alpha4": 0,
      "22.0.0-alpha3": 0,
      "22.0.0-alpha2": 0,
      "22.0.0-alpha10": 0,
      "22.0.0-alpha1": 0,
      "21.0.3": 0,
      "21.0.2": 0,
      "21.0.1": 0,
      "21.0.0": 0,
      "21.0.0-rc1": 0,
      "21.0.0-beta2": 0,
      "21.0.0-beta1": 0,
      "21.0.0-alpha9": 123,
      "21.0.0-alpha8": 227,
      "21.0.0-alpha7": 6,
      "21.0.0-alpha6": 292,
      "21.0.0-alpha5": 2,
      "21.0.0-alpha4": 2,
      "21.0.0-alpha3": 2,
      "21.0.0-alpha2": 1,
      "21.0.0-alpha13": 56,
      "21.0.0-alpha12": 24,
      "21.0.0-alpha11": 28,
      "21.0.0-alpha10": 28,
      "21.0.0-alpha1": 1,
      "21.0.0-alpha0.b163d3a8c": 1,
      "21.0.0-alpha0.29f1db3de": 1,
      "20.0.5": 0,
      "20.0.4": 0,
      "20.0.3": 0,
      "20.0.2": 0,
      "20.0.1": 0,
      "20.0.0": 1074,
      "20.0.0-rc1": 2,
      "20.0.0-beta2": 1,
      "20.0.0-beta1": 1,
      "20.0.0-alpha6": 1,
      "20.0.0-alpha5": 1,
      "20.0.0-alpha4": 1,
      "20.0.0-alpha3": 61,
      "20.0.0-alpha2": 1,
      "20.0.0-alpha1": 1,
      "5.0.0-alpha1": 1,
      "4.3.0": 9097,
      "4.3.0-beta1": 0,
      "4.3.0-alpha1": 0,
      "4.2.0": 1114,
      "4.2.0-alpha1": 42,
      "4.1.1": 2217,
      "4.1.0": 4,
      "4.1.0-beta2": 0,
      "4.1.0-beta1": 0,
      "4.1.0-alpha3": 0,
      "4.1.0-alpha2": 0
    },
    {
      "date": "05/07/2021",
      "22.0.0-beta1": 0,
      "22.0.0-alpha9": 0,
      "22.0.0-alpha8": 0,
      "22.0.0-alpha7": 0,
      "22.0.0-alpha6": 0,
      "22.0.0-alpha5": 0,
      "22.0.0-alpha4": 0,
      "22.0.0-alpha3": 0,
      "22.0.0-alpha2": 0,
      "22.0.0-alpha10": 0,
      "22.0.0-alpha1": 0,
      "21.0.3": 0,
      "21.0.2": 0,
      "21.0.1": 0,
      "21.0.0": 0,
      "21.0.0-rc1": 0,
      "21.0.0-beta2": 0,
      "21.0.0-beta1": 0,
      "21.0.0-alpha9": 11,
      "21.0.0-alpha8": 408,
      "21.0.0-alpha7": 1,
      "21.0.0-alpha6": 111,
      "21.0.0-alpha5": 1,
      "21.0.0-alpha4": 0,
      "21.0.0-alpha3": 0,
      "21.0.0-alpha2": 2,
      "21.0.0-alpha13": 497,
      "21.0.0-alpha12": 2,
      "21.0.0-alpha11": 2,
      "21.0.0-alpha10": 1,
      "21.0.0-alpha1": 0,
      "21.0.0-alpha0.b163d3a8c": 0,
      "21.0.0-alpha0.29f1db3de": 0,
      "20.0.5": 0,
      "20.0.4": 0,
      "20.0.3": 0,
      "20.0.2": 0,
      "20.0.1": 0,
      "20.0.0": 1038,
      "20.0.0-rc1": 0,
      "20.0.0-beta2": 0,
      "20.0.0-beta1": 0,
      "20.0.0-alpha6": 0,
      "20.0.0-alpha5": 0,
      "20.0.0-alpha4": 1,
      "20.0.0-alpha3": 19,
      "20.0.0-alpha2": 0,
      "20.0.0-alpha1": 0,
      "5.0.0-alpha1": 0,
      "4.3.0": 9071,
      "4.3.0-beta1": 0,
      "4.3.0-alpha1": 2,
      "4.2.0": 1112,
      "4.2.0-alpha1": 40,
      "4.1.1": 1996,
      "4.1.0": 1,
      "4.1.0-beta2": 0,
      "4.1.0-beta1": 0,
      "4.1.0-alpha3": 0,
      "4.1.0-alpha2": 0
    },
    {
      "date": "12/07/2021",
      "22.0.0-beta1": 0,
      "22.0.0-alpha9": 0,
      "22.0.0-alpha8": 0,
      "22.0.0-alpha7": 0,
      "22.0.0-alpha6": 0,
      "22.0.0-alpha5": 0,
      "22.0.0-alpha4": 0,
      "22.0.0-alpha3": 0,
      "22.0.0-alpha2": 0,
      "22.0.0-alpha10": 0,
      "22.0.0-alpha1": 0,
      "21.0.3": 0,
      "21.0.2": 0,
      "21.0.1": 0,
      "21.0.0": 0,
      "21.0.0-rc1": 0,
      "21.0.0-beta2": 0,
      "21.0.0-beta1": 0,
      "21.0.0-alpha9": 8,
      "21.0.0-alpha8": 105,
      "21.0.0-alpha7": 4,
      "21.0.0-alpha6": 4,
      "21.0.0-alpha5": 4,
      "21.0.0-alpha4": 3,
      "21.0.0-alpha3": 3,
      "21.0.0-alpha2": 3,
      "21.0.0-alpha13": 774,
      "21.0.0-alpha12": 4,
      "21.0.0-alpha11": 5,
      "21.0.0-alpha10": 5,
      "21.0.0-alpha1": 2,
      "21.0.0-alpha0.b163d3a8c": 2,
      "21.0.0-alpha0.29f1db3de": 2,
      "20.0.5": 0,
      "20.0.4": 0,
      "20.0.3": 0,
      "20.0.2": 0,
      "20.0.1": 0,
      "20.0.0": 1128,
      "20.0.0-rc1": 3,
      "20.0.0-beta2": 2,
      "20.0.0-beta1": 2,
      "20.0.0-alpha6": 2,
      "20.0.0-alpha5": 5,
      "20.0.0-alpha4": 3,
      "20.0.0-alpha3": 103,
      "20.0.0-alpha2": 2,
      "20.0.0-alpha1": 1,
      "5.0.0-alpha1": 1,
      "4.3.0": 9149,
      "4.3.0-beta1": 1,
      "4.3.0-alpha1": 3,
      "4.2.0": 1098,
      "4.2.0-alpha1": 41,
      "4.1.1": 2244,
      "4.1.0": 6,
      "4.1.0-beta2": 2,
      "4.1.0-beta1": 1,
      "4.1.0-alpha3": 2,
      "4.1.0-alpha2": 2
    },
    {
      "date": "19/07/2021",
      "22.0.0-beta1": 0,
      "22.0.0-alpha9": 0,
      "22.0.0-alpha8": 0,
      "22.0.0-alpha7": 0,
      "22.0.0-alpha6": 0,
      "22.0.0-alpha5": 0,
      "22.0.0-alpha4": 0,
      "22.0.0-alpha3": 0,
      "22.0.0-alpha2": 0,
      "22.0.0-alpha10": 0,
      "22.0.0-alpha1": 0,
      "21.0.3": 0,
      "21.0.2": 0,
      "21.0.1": 0,
      "21.0.0": 0,
      "21.0.0-rc1": 0,
      "21.0.0-beta2": 0,
      "21.0.0-beta1": 0,
      "21.0.0-alpha9": 4,
      "21.0.0-alpha8": 5,
      "21.0.0-alpha7": 2,
      "21.0.0-alpha6": 2,
      "21.0.0-alpha5": 1,
      "21.0.0-alpha4": 2,
      "21.0.0-alpha3": 3,
      "21.0.0-alpha2": 3,
      "21.0.0-alpha13": 306,
      "21.0.0-alpha12": 2,
      "21.0.0-alpha11": 3,
      "21.0.0-alpha10": 1,
      "21.0.0-alpha1": 2,
      "21.0.0-alpha0.b163d3a8c": 1,
      "21.0.0-alpha0.29f1db3de": 1,
      "20.0.5": 0,
      "20.0.4": 0,
      "20.0.3": 0,
      "20.0.2": 0,
      "20.0.1": 0,
      "20.0.0": 1258,
      "20.0.0-rc1": 1,
      "20.0.0-beta2": 3,
      "20.0.0-beta1": 6,
      "20.0.0-alpha6": 1,
      "20.0.0-alpha5": 1,
      "20.0.0-alpha4": 0,
      "20.0.0-alpha3": 56,
      "20.0.0-alpha2": 1,
      "20.0.0-alpha1": 1,
      "5.0.0-alpha1": 1,
      "4.3.0": 8992,
      "4.3.0-beta1": 1,
      "4.3.0-alpha1": 0,
      "4.2.0": 1356,
      "4.2.0-alpha1": 40,
      "4.1.1": 2249,
      "4.1.0": 10,
      "4.1.0-beta2": 2,
      "4.1.0-beta1": 1,
      "4.1.0-alpha3": 0,
      "4.1.0-alpha2": 0
    },
    {
      "date": "26/07/2021",
      "22.0.0-beta1": 0,
      "22.0.0-alpha9": 0,
      "22.0.0-alpha8": 0,
      "22.0.0-alpha7": 0,
      "22.0.0-alpha6": 0,
      "22.0.0-alpha5": 0,
      "22.0.0-alpha4": 0,
      "22.0.0-alpha3": 0,
      "22.0.0-alpha2": 0,
      "22.0.0-alpha10": 0,
      "22.0.0-alpha1": 0,
      "21.0.3": 0,
      "21.0.2": 0,
      "21.0.1": 0,
      "21.0.0": 0,
      "21.0.0-rc1": 0,
      "21.0.0-beta2": 0,
      "21.0.0-beta1": 0,
      "21.0.0-alpha9": 3,
      "21.0.0-alpha8": 2,
      "21.0.0-alpha7": 1,
      "21.0.0-alpha6": 1,
      "21.0.0-alpha5": 2,
      "21.0.0-alpha4": 1,
      "21.0.0-alpha3": 0,
      "21.0.0-alpha2": 1,
      "21.0.0-alpha13": 281,
      "21.0.0-alpha12": 3,
      "21.0.0-alpha11": 2,
      "21.0.0-alpha10": 2,
      "21.0.0-alpha1": 0,
      "21.0.0-alpha0.b163d3a8c": 0,
      "21.0.0-alpha0.29f1db3de": 0,
      "20.0.5": 0,
      "20.0.4": 0,
      "20.0.3": 0,
      "20.0.2": 0,
      "20.0.1": 77,
      "20.0.0": 1565,
      "20.0.0-rc1": 0,
      "20.0.0-beta2": 0,
      "20.0.0-beta1": 0,
      "20.0.0-alpha6": 0,
      "20.0.0-alpha5": 0,
      "20.0.0-alpha4": 0,
      "20.0.0-alpha3": 92,
      "20.0.0-alpha2": 0,
      "20.0.0-alpha1": 0,
      "5.0.0-alpha1": 0,
      "4.3.0": 9292,
      "4.3.0-beta1": 0,
      "4.3.0-alpha1": 0,
      "4.2.0": 1393,
      "4.2.0-alpha1": 46,
      "4.1.1": 2036,
      "4.1.0": 33,
      "4.1.0-beta2": 0,
      "4.1.0-beta1": 0,
      "4.1.0-alpha3": 0,
      "4.1.0-alpha2": 0
    },
    {
      "date": "02/08/2021",
      "22.0.0-beta1": 0,
      "22.0.0-alpha9": 0,
      "22.0.0-alpha8": 0,
      "22.0.0-alpha7": 0,
      "22.0.0-alpha6": 0,
      "22.0.0-alpha5": 0,
      "22.0.0-alpha4": 0,
      "22.0.0-alpha3": 0,
      "22.0.0-alpha2": 0,
      "22.0.0-alpha10": 0,
      "22.0.0-alpha1": 0,
      "21.0.3": 0,
      "21.0.2": 0,
      "21.0.1": 0,
      "21.0.0": 0,
      "21.0.0-rc1": 0,
      "21.0.0-beta2": 0,
      "21.0.0-beta1": 46,
      "21.0.0-alpha9": 3,
      "21.0.0-alpha8": 1,
      "21.0.0-alpha7": 1,
      "21.0.0-alpha6": 1,
      "21.0.0-alpha5": 1,
      "21.0.0-alpha4": 1,
      "21.0.0-alpha3": 2,
      "21.0.0-alpha2": 2,
      "21.0.0-alpha13": 281,
      "21.0.0-alpha12": 1,
      "21.0.0-alpha11": 1,
      "21.0.0-alpha10": 1,
      "21.0.0-alpha1": 2,
      "21.0.0-alpha0.b163d3a8c": 2,
      "21.0.0-alpha0.29f1db3de": 2,
      "20.0.5": 0,
      "20.0.4": 0,
      "20.0.3": 0,
      "20.0.2": 0,
      "20.0.1": 853,
      "20.0.0": 905,
      "20.0.0-rc1": 2,
      "20.0.0-beta2": 2,
      "20.0.0-beta1": 1,
      "20.0.0-alpha6": 1,
      "20.0.0-alpha5": 1,
      "20.0.0-alpha4": 1,
      "20.0.0-alpha3": 81,
      "20.0.0-alpha2": 1,
      "20.0.0-alpha1": 1,
      "5.0.0-alpha1": 1,
      "4.3.0": 8446,
      "4.3.0-beta1": 1,
      "4.3.0-alpha1": 1,
      "4.2.0": 1171,
      "4.2.0-alpha1": 47,
      "4.1.1": 2939,
      "4.1.0": 12,
      "4.1.0-beta2": 1,
      "4.1.0-beta1": 1,
      "4.1.0-alpha3": 1,
      "4.1.0-alpha2": 1
    },
    {
      "date": "09/08/2021",
      "22.0.0-beta1": 0,
      "22.0.0-alpha9": 0,
      "22.0.0-alpha8": 0,
      "22.0.0-alpha7": 0,
      "22.0.0-alpha6": 0,
      "22.0.0-alpha5": 0,
      "22.0.0-alpha4": 0,
      "22.0.0-alpha3": 0,
      "22.0.0-alpha2": 0,
      "22.0.0-alpha10": 0,
      "22.0.0-alpha1": 81,
      "21.0.3": 0,
      "21.0.2": 0,
      "21.0.1": 0,
      "21.0.0": 0,
      "21.0.0-rc1": 0,
      "21.0.0-beta2": 0,
      "21.0.0-beta1": 254,
      "21.0.0-alpha9": 1,
      "21.0.0-alpha8": 2,
      "21.0.0-alpha7": 0,
      "21.0.0-alpha6": 0,
      "21.0.0-alpha5": 2,
      "21.0.0-alpha4": 1,
      "21.0.0-alpha3": 1,
      "21.0.0-alpha2": 1,
      "21.0.0-alpha13": 134,
      "21.0.0-alpha12": 0,
      "21.0.0-alpha11": 0,
      "21.0.0-alpha10": 0,
      "21.0.0-alpha1": 1,
      "21.0.0-alpha0.b163d3a8c": 1,
      "21.0.0-alpha0.29f1db3de": 1,
      "20.0.5": 0,
      "20.0.4": 0,
      "20.0.3": 0,
      "20.0.2": 99,
      "20.0.1": 1158,
      "20.0.0": 394,
      "20.0.0-rc1": 1,
      "20.0.0-beta2": 1,
      "20.0.0-beta1": 1,
      "20.0.0-alpha6": 1,
      "20.0.0-alpha5": 1,
      "20.0.0-alpha4": 1,
      "20.0.0-alpha3": 76,
      "20.0.0-alpha2": 1,
      "20.0.0-alpha1": 1,
      "5.0.0-alpha1": 1,
      "4.3.0": 8185,
      "4.3.0-beta1": 1,
      "4.3.0-alpha1": 1,
      "4.2.0": 1110,
      "4.2.0-alpha1": 43,
      "4.1.1": 4763,
      "4.1.0": 1,
      "4.1.0-beta2": 1,
      "4.1.0-beta1": 1,
      "4.1.0-alpha3": 1,
      "4.1.0-alpha2": 1
    },
    {
      "date": "16/08/2021",
      "22.0.0-beta1": 0,
      "22.0.0-alpha9": 0,
      "22.0.0-alpha8": 0,
      "22.0.0-alpha7": 0,
      "22.0.0-alpha6": 0,
      "22.0.0-alpha5": 0,
      "22.0.0-alpha4": 0,
      "22.0.0-alpha3": 0,
      "22.0.0-alpha2": 0,
      "22.0.0-alpha10": 0,
      "22.0.0-alpha1": 133,
      "21.0.3": 0,
      "21.0.2": 0,
      "21.0.1": 0,
      "21.0.0": 0,
      "21.0.0-rc1": 0,
      "21.0.0-beta2": 400,
      "21.0.0-beta1": 227,
      "21.0.0-alpha9": 3,
      "21.0.0-alpha8": 3,
      "21.0.0-alpha7": 2,
      "21.0.0-alpha6": 2,
      "21.0.0-alpha5": 2,
      "21.0.0-alpha4": 2,
      "21.0.0-alpha3": 2,
      "21.0.0-alpha2": 2,
      "21.0.0-alpha13": 199,
      "21.0.0-alpha12": 2,
      "21.0.0-alpha11": 2,
      "21.0.0-alpha10": 2,
      "21.0.0-alpha1": 2,
      "21.0.0-alpha0.b163d3a8c": 2,
      "21.0.0-alpha0.29f1db3de": 2,
      "20.0.5": 0,
      "20.0.4": 0,
      "20.0.3": 0,
      "20.0.2": 1163,
      "20.0.1": 376,
      "20.0.0": 261,
      "20.0.0-rc1": 2,
      "20.0.0-beta2": 2,
      "20.0.0-beta1": 6,
      "20.0.0-alpha6": 2,
      "20.0.0-alpha5": 2,
      "20.0.0-alpha4": 14,
      "20.0.0-alpha3": 16,
      "20.0.0-alpha2": 2,
      "20.0.0-alpha1": 2,
      "5.0.0-alpha1": 2,
      "4.3.0": 8352,
      "4.3.0-beta1": 1,
      "4.3.0-alpha1": 2,
      "4.2.0": 1284,
      "4.2.0-alpha1": 59,
      "4.1.1": 2144,
      "4.1.0": 8,
      "4.1.0-beta2": 1,
      "4.1.0-beta1": 1,
      "4.1.0-alpha3": 1,
      "4.1.0-alpha2": 1
    },
    {
      "date": "23/08/2021",
      "22.0.0-beta1": 0,
      "22.0.0-alpha9": 0,
      "22.0.0-alpha8": 0,
      "22.0.0-alpha7": 0,
      "22.0.0-alpha6": 0,
      "22.0.0-alpha5": 0,
      "22.0.0-alpha4": 0,
      "22.0.0-alpha3": 0,
      "22.0.0-alpha2": 0,
      "22.0.0-alpha10": 0,
      "22.0.0-alpha1": 153,
      "21.0.3": 0,
      "21.0.2": 0,
      "21.0.1": 0,
      "21.0.0": 0,
      "21.0.0-rc1": 39,
      "21.0.0-beta2": 628,
      "21.0.0-beta1": 4,
      "21.0.0-alpha9": 2,
      "21.0.0-alpha8": 1,
      "21.0.0-alpha7": 1,
      "21.0.0-alpha6": 2,
      "21.0.0-alpha5": 1,
      "21.0.0-alpha4": 1,
      "21.0.0-alpha3": 1,
      "21.0.0-alpha2": 1,
      "21.0.0-alpha13": 47,
      "21.0.0-alpha12": 1,
      "21.0.0-alpha11": 1,
      "21.0.0-alpha10": 1,
      "21.0.0-alpha1": 1,
      "21.0.0-alpha0.b163d3a8c": 1,
      "21.0.0-alpha0.29f1db3de": 1,
      "20.0.5": 0,
      "20.0.4": 0,
      "20.0.3": 0,
      "20.0.2": 1079,
      "20.0.1": 187,
      "20.0.0": 175,
      "20.0.0-rc1": 1,
      "20.0.0-beta2": 1,
      "20.0.0-beta1": 1,
      "20.0.0-alpha6": 1,
      "20.0.0-alpha5": 1,
      "20.0.0-alpha4": 2,
      "20.0.0-alpha3": 6,
      "20.0.0-alpha2": 1,
      "20.0.0-alpha1": 1,
      "5.0.0-alpha1": 1,
      "4.3.0": 8803,
      "4.3.0-beta1": 1,
      "4.3.0-alpha1": 1,
      "4.2.0": 1639,
      "4.2.0-alpha1": 43,
      "4.1.1": 2519,
      "4.1.0": 12,
      "4.1.0-beta2": 1,
      "4.1.0-beta1": 1,
      "4.1.0-alpha3": 1,
      "4.1.0-alpha2": 1
    },
    {
      "date": "30/08/2021",
      "22.0.0-beta1": 0,
      "22.0.0-alpha9": 0,
      "22.0.0-alpha8": 0,
      "22.0.0-alpha7": 0,
      "22.0.0-alpha6": 0,
      "22.0.0-alpha5": 0,
      "22.0.0-alpha4": 0,
      "22.0.0-alpha3": 8,
      "22.0.0-alpha2": 60,
      "22.0.0-alpha10": 0,
      "22.0.0-alpha1": 82,
      "21.0.3": 0,
      "21.0.2": 0,
      "21.0.1": 0,
      "21.0.0": 0,
      "21.0.0-rc1": 287,
      "21.0.0-beta2": 326,
      "21.0.0-beta1": 8,
      "21.0.0-alpha9": 1,
      "21.0.0-alpha8": 1,
      "21.0.0-alpha7": 2,
      "21.0.0-alpha6": 3,
      "21.0.0-alpha5": 1,
      "21.0.0-alpha4": 1,
      "21.0.0-alpha3": 1,
      "21.0.0-alpha2": 1,
      "21.0.0-alpha13": 14,
      "21.0.0-alpha12": 1,
      "21.0.0-alpha11": 2,
      "21.0.0-alpha10": 1,
      "21.0.0-alpha1": 1,
      "21.0.0-alpha0.b163d3a8c": 2,
      "21.0.0-alpha0.29f1db3de": 1,
      "20.0.5": 0,
      "20.0.4": 0,
      "20.0.3": 777,
      "20.0.2": 465,
      "20.0.1": 111,
      "20.0.0": 126,
      "20.0.0-rc1": 1,
      "20.0.0-beta2": 1,
      "20.0.0-beta1": 2,
      "20.0.0-alpha6": 1,
      "20.0.0-alpha5": 0,
      "20.0.0-alpha4": 1,
      "20.0.0-alpha3": 0,
      "20.0.0-alpha2": 1,
      "20.0.0-alpha1": 0,
      "5.0.0-alpha1": 0,
      "4.3.0": 9486,
      "4.3.0-beta1": 0,
      "4.3.0-alpha1": 0,
      "4.2.0": 1653,
      "4.2.0-alpha1": 51,
      "4.1.1": 2184,
      "4.1.0": 32,
      "4.1.0-beta2": 0,
      "4.1.0-beta1": 0,
      "4.1.0-alpha3": 1,
      "4.1.0-alpha2": 0
    },
    {
      "date": "06/09/2021",
      "22.0.0-beta1": 0,
      "22.0.0-alpha9": 0,
      "22.0.0-alpha8": 0,
      "22.0.0-alpha7": 0,
      "22.0.0-alpha6": 0,
      "22.0.0-alpha5": 0,
      "22.0.0-alpha4": 41,
      "22.0.0-alpha3": 171,
      "22.0.0-alpha2": 5,
      "22.0.0-alpha10": 0,
      "22.0.0-alpha1": 40,
      "21.0.3": 0,
      "21.0.2": 0,
      "21.0.1": 0,
      "21.0.0": 0,
      "21.0.0-rc1": 491,
      "21.0.0-beta2": 132,
      "21.0.0-beta1": 4,
      "21.0.0-alpha9": 2,
      "21.0.0-alpha8": 3,
      "21.0.0-alpha7": 2,
      "21.0.0-alpha6": 2,
      "21.0.0-alpha5": 2,
      "21.0.0-alpha4": 2,
      "21.0.0-alpha3": 2,
      "21.0.0-alpha2": 2,
      "21.0.0-alpha13": 8,
      "21.0.0-alpha12": 2,
      "21.0.0-alpha11": 2,
      "21.0.0-alpha10": 2,
      "21.0.0-alpha1": 2,
      "21.0.0-alpha0.b163d3a8c": 2,
      "21.0.0-alpha0.29f1db3de": 2,
      "20.0.5": 0,
      "20.0.4": 601,
      "20.0.3": 676,
      "20.0.2": 351,
      "20.0.1": 89,
      "20.0.0": 121,
      "20.0.0-rc1": 2,
      "20.0.0-beta2": 2,
      "20.0.0-beta1": 2,
      "20.0.0-alpha6": 2,
      "20.0.0-alpha5": 2,
      "20.0.0-alpha4": 2,
      "20.0.0-alpha3": 2,
      "20.0.0-alpha2": 2,
      "20.0.0-alpha1": 2,
      "5.0.0-alpha1": 2,
      "4.3.0": 11188,
      "4.3.0-beta1": 2,
      "4.3.0-alpha1": 2,
      "4.2.0": 1483,
      "4.2.0-alpha1": 48,
      "4.1.1": 2578,
      "4.1.0": 13,
      "4.1.0-beta2": 2,
      "4.1.0-beta1": 2,
      "4.1.0-alpha3": 2,
      "4.1.0-alpha2": 2
    },
    {
      "date": "13/09/2021",
      "22.0.0-beta1": 0,
      "22.0.0-alpha9": 0,
      "22.0.0-alpha8": 0,
      "22.0.0-alpha7": 0,
      "22.0.0-alpha6": 0,
      "22.0.0-alpha5": 245,
      "22.0.0-alpha4": 11,
      "22.0.0-alpha3": 145,
      "22.0.0-alpha2": 0,
      "22.0.0-alpha10": 0,
      "22.0.0-alpha1": 3,
      "21.0.3": 0,
      "21.0.2": 0,
      "21.0.1": 0,
      "21.0.0": 1351,
      "21.0.0-rc1": 201,
      "21.0.0-beta2": 26,
      "21.0.0-beta1": 2,
      "21.0.0-alpha9": 0,
      "21.0.0-alpha8": 2,
      "21.0.0-alpha7": 0,
      "21.0.0-alpha6": 0,
      "21.0.0-alpha5": 1,
      "21.0.0-alpha4": 0,
      "21.0.0-alpha3": 0,
      "21.0.0-alpha2": 0,
      "21.0.0-alpha13": 5,
      "21.0.0-alpha12": 0,
      "21.0.0-alpha11": 0,
      "21.0.0-alpha10": 0,
      "21.0.0-alpha1": 0,
      "21.0.0-alpha0.b163d3a8c": 0,
      "21.0.0-alpha0.29f1db3de": 0,
      "20.0.5": 0,
      "20.0.4": 290,
      "20.0.3": 419,
      "20.0.2": 261,
      "20.0.1": 44,
      "20.0.0": 105,
      "20.0.0-rc1": 0,
      "20.0.0-beta2": 0,
      "20.0.0-beta1": 1,
      "20.0.0-alpha6": 0,
      "20.0.0-alpha5": 0,
      "20.0.0-alpha4": 1,
      "20.0.0-alpha3": 0,
      "20.0.0-alpha2": 0,
      "20.0.0-alpha1": 0,
      "5.0.0-alpha1": 0,
      "4.3.0": 10652,
      "4.3.0-beta1": 0,
      "4.3.0-alpha1": 1,
      "4.2.0": 1553,
      "4.2.0-alpha1": 40,
      "4.1.1": 2580,
      "4.1.0": 7,
      "4.1.0-beta2": 0,
      "4.1.0-beta1": 0,
      "4.1.0-alpha3": 0,
      "4.1.0-alpha2": 0
    },
    {
      "date": "20/09/2021",
      "22.0.0-beta1": 0,
      "22.0.0-alpha9": 0,
      "22.0.0-alpha8": 0,
      "22.0.0-alpha7": 0,
      "22.0.0-alpha6": 69,
      "22.0.0-alpha5": 450,
      "22.0.0-alpha4": 2,
      "22.0.0-alpha3": 3,
      "22.0.0-alpha2": 3,
      "22.0.0-alpha10": 0,
      "22.0.0-alpha1": 2,
      "21.0.3": 0,
      "21.0.2": 0,
      "21.0.1": 991,
      "21.0.0": 558,
      "21.0.0-rc1": 32,
      "21.0.0-beta2": 34,
      "21.0.0-beta1": 5,
      "21.0.0-alpha9": 0,
      "21.0.0-alpha8": 2,
      "21.0.0-alpha7": 0,
      "21.0.0-alpha6": 0,
      "21.0.0-alpha5": 0,
      "21.0.0-alpha4": 0,
      "21.0.0-alpha3": 0,
      "21.0.0-alpha2": 0,
      "21.0.0-alpha13": 3,
      "21.0.0-alpha12": 0,
      "21.0.0-alpha11": 0,
      "21.0.0-alpha10": 0,
      "21.0.0-alpha1": 0,
      "21.0.0-alpha0.b163d3a8c": 0,
      "21.0.0-alpha0.29f1db3de": 0,
      "20.0.5": 0,
      "20.0.4": 286,
      "20.0.3": 198,
      "20.0.2": 180,
      "20.0.1": 87,
      "20.0.0": 111,
      "20.0.0-rc1": 0,
      "20.0.0-beta2": 3,
      "20.0.0-beta1": 0,
      "20.0.0-alpha6": 0,
      "20.0.0-alpha5": 0,
      "20.0.0-alpha4": 0,
      "20.0.0-alpha3": 0,
      "20.0.0-alpha2": 0,
      "20.0.0-alpha1": 0,
      "5.0.0-alpha1": 0,
      "4.3.0": 10901,
      "4.3.0-beta1": 0,
      "4.3.0-alpha1": 0,
      "4.2.0": 1613,
      "4.2.0-alpha1": 42,
      "4.1.1": 2477,
      "4.1.0": 5,
      "4.1.0-beta2": 1,
      "4.1.0-beta1": 1,
      "4.1.0-alpha3": 1,
      "4.1.0-alpha2": 1
    },
    {
      "date": "27/09/2021",
      "22.0.0-beta1": 0,
      "22.0.0-alpha9": 0,
      "22.0.0-alpha8": 0,
      "22.0.0-alpha7": 0,
      "22.0.0-alpha6": 340,
      "22.0.0-alpha5": 159,
      "22.0.0-alpha4": 3,
      "22.0.0-alpha3": 6,
      "22.0.0-alpha2": 3,
      "22.0.0-alpha10": 0,
      "22.0.0-alpha1": 3,
      "21.0.3": 0,
      "21.0.2": 132,
      "21.0.1": 942,
      "21.0.0": 297,
      "21.0.0-rc1": 48,
      "21.0.0-beta2": 47,
      "21.0.0-beta1": 8,
      "21.0.0-alpha9": 3,
      "21.0.0-alpha8": 7,
      "21.0.0-alpha7": 4,
      "21.0.0-alpha6": 6,
      "21.0.0-alpha5": 4,
      "21.0.0-alpha4": 3,
      "21.0.0-alpha3": 4,
      "21.0.0-alpha2": 4,
      "21.0.0-alpha13": 8,
      "21.0.0-alpha12": 5,
      "21.0.0-alpha11": 4,
      "21.0.0-alpha10": 5,
      "21.0.0-alpha1": 3,
      "21.0.0-alpha0.b163d3a8c": 2,
      "21.0.0-alpha0.29f1db3de": 3,
      "20.0.5": 0,
      "20.0.4": 279,
      "20.0.3": 152,
      "20.0.2": 161,
      "20.0.1": 51,
      "20.0.0": 77,
      "20.0.0-rc1": 4,
      "20.0.0-beta2": 2,
      "20.0.0-beta1": 2,
      "20.0.0-alpha6": 4,
      "20.0.0-alpha5": 3,
      "20.0.0-alpha4": 6,
      "20.0.0-alpha3": 3,
      "20.0.0-alpha2": 2,
      "20.0.0-alpha1": 2,
      "5.0.0-alpha1": 3,
      "4.3.0": 10323,
      "4.3.0-beta1": 2,
      "4.3.0-alpha1": 3,
      "4.2.0": 1697,
      "4.2.0-alpha1": 57,
      "4.1.1": 2512,
      "4.1.0": 3,
      "4.1.0-beta2": 2,
      "4.1.0-beta1": 1,
      "4.1.0-alpha3": 2,
      "4.1.0-alpha2": 1
    },
    {
      "date": "04/10/2021",
      "22.0.0-beta1": 0,
      "22.0.0-alpha9": 0,
      "22.0.0-alpha8": 0,
      "22.0.0-alpha7": 0,
      "22.0.0-alpha6": 465,
      "22.0.0-alpha5": 47,
      "22.0.0-alpha4": 1,
      "22.0.0-alpha3": 2,
      "22.0.0-alpha2": 2,
      "22.0.0-alpha10": 0,
      "22.0.0-alpha1": 2,
      "21.0.3": 0,
      "21.0.2": 1026,
      "21.0.1": 485,
      "21.0.0": 240,
      "21.0.0-rc1": 9,
      "21.0.0-beta2": 29,
      "21.0.0-beta1": 7,
      "21.0.0-alpha9": 2,
      "21.0.0-alpha8": 2,
      "21.0.0-alpha7": 2,
      "21.0.0-alpha6": 3,
      "21.0.0-alpha5": 3,
      "21.0.0-alpha4": 2,
      "21.0.0-alpha3": 1,
      "21.0.0-alpha2": 2,
      "21.0.0-alpha13": 3,
      "21.0.0-alpha12": 2,
      "21.0.0-alpha11": 2,
      "21.0.0-alpha10": 2,
      "21.0.0-alpha1": 4,
      "21.0.0-alpha0.b163d3a8c": 4,
      "21.0.0-alpha0.29f1db3de": 1,
      "20.0.5": 0,
      "20.0.4": 282,
      "20.0.3": 111,
      "20.0.2": 155,
      "20.0.1": 40,
      "20.0.0": 83,
      "20.0.0-rc1": 2,
      "20.0.0-beta2": 4,
      "20.0.0-beta1": 1,
      "20.0.0-alpha6": 1,
      "20.0.0-alpha5": 1,
      "20.0.0-alpha4": 2,
      "20.0.0-alpha3": 1,
      "20.0.0-alpha2": 1,
      "20.0.0-alpha1": 1,
      "5.0.0-alpha1": 1,
      "4.3.0": 10467,
      "4.3.0-beta1": 0,
      "4.3.0-alpha1": 0,
      "4.2.0": 1497,
      "4.2.0-alpha1": 18,
      "4.1.1": 2491,
      "4.1.0": 8,
      "4.1.0-beta2": 0,
      "4.1.0-beta1": 0,
      "4.1.0-alpha3": 0,
      "4.1.0-alpha2": 0
    },
    {
      "date": "11/10/2021",
      "22.0.0-beta1": 0,
      "22.0.0-alpha9": 0,
      "22.0.0-alpha8": 0,
      "22.0.0-alpha7": 44,
      "22.0.0-alpha6": 384,
      "22.0.0-alpha5": 4,
      "22.0.0-alpha4": 0,
      "22.0.0-alpha3": 0,
      "22.0.0-alpha2": 0,
      "22.0.0-alpha10": 0,
      "22.0.0-alpha1": 0,
      "21.0.3": 0,
      "21.0.2": 978,
      "21.0.1": 294,
      "21.0.0": 147,
      "21.0.0-rc1": 6,
      "21.0.0-beta2": 17,
      "21.0.0-beta1": 0,
      "21.0.0-alpha9": 0,
      "21.0.0-alpha8": 1,
      "21.0.0-alpha7": 0,
      "21.0.0-alpha6": 0,
      "21.0.0-alpha5": 0,
      "21.0.0-alpha4": 0,
      "21.0.0-alpha3": 0,
      "21.0.0-alpha2": 12,
      "21.0.0-alpha13": 3,
      "21.0.0-alpha12": 0,
      "21.0.0-alpha11": 0,
      "21.0.0-alpha10": 0,
      "21.0.0-alpha1": 0,
      "21.0.0-alpha0.b163d3a8c": 0,
      "21.0.0-alpha0.29f1db3de": 0,
      "20.0.5": 161,
      "20.0.4": 276,
      "20.0.3": 103,
      "20.0.2": 130,
      "20.0.1": 42,
      "20.0.0": 70,
      "20.0.0-rc1": 0,
      "20.0.0-beta2": 0,
      "20.0.0-beta1": 0,
      "20.0.0-alpha6": 0,
      "20.0.0-alpha5": 0,
      "20.0.0-alpha4": 0,
      "20.0.0-alpha3": 0,
      "20.0.0-alpha2": 0,
      "20.0.0-alpha1": 0,
      "5.0.0-alpha1": 0,
      "4.3.0": 10979,
      "4.3.0-beta1": 0,
      "4.3.0-alpha1": 0,
      "4.2.0": 1674,
      "4.2.0-alpha1": 51,
      "4.1.1": 2552,
      "4.1.0": 2,
      "4.1.0-beta2": 0,
      "4.1.0-beta1": 0,
      "4.1.0-alpha3": 0,
      "4.1.0-alpha2": 0
    },
    {
      "date": "18/10/2021",
      "22.0.0-beta1": 0,
      "22.0.0-alpha9": 68,
      "22.0.0-alpha8": 24,
      "22.0.0-alpha7": 127,
      "22.0.0-alpha6": 614,
      "22.0.0-alpha5": 4,
      "22.0.0-alpha4": 3,
      "22.0.0-alpha3": 1,
      "22.0.0-alpha2": 1,
      "22.0.0-alpha10": 178,
      "22.0.0-alpha1": 1,
      "21.0.3": 603,
      "21.0.2": 819,
      "21.0.1": 225,
      "21.0.0": 190,
      "21.0.0-rc1": 5,
      "21.0.0-beta2": 24,
      "21.0.0-beta1": 1,
      "21.0.0-alpha9": 0,
      "21.0.0-alpha8": 0,
      "21.0.0-alpha7": 0,
      "21.0.0-alpha6": 0,
      "21.0.0-alpha5": 0,
      "21.0.0-alpha4": 0,
      "21.0.0-alpha3": 0,
      "21.0.0-alpha2": 4,
      "21.0.0-alpha13": 2,
      "21.0.0-alpha12": 0,
      "21.0.0-alpha11": 0,
      "21.0.0-alpha10": 0,
      "21.0.0-alpha1": 0,
      "21.0.0-alpha0.b163d3a8c": 0,
      "21.0.0-alpha0.29f1db3de": 0,
      "20.0.5": 211,
      "20.0.4": 42,
      "20.0.3": 88,
      "20.0.2": 160,
      "20.0.1": 29,
      "20.0.0": 83,
      "20.0.0-rc1": 0,
      "20.0.0-beta2": 0,
      "20.0.0-beta1": 0,
      "20.0.0-alpha6": 0,
      "20.0.0-alpha5": 0,
      "20.0.0-alpha4": 0,
      "20.0.0-alpha3": 0,
      "20.0.0-alpha2": 0,
      "20.0.0-alpha1": 0,
      "5.0.0-alpha1": 0,
      "4.3.0": 11926,
      "4.3.0-beta1": 0,
      "4.3.0-alpha1": 0,
      "4.2.0": 1584,
      "4.2.0-alpha1": 42,
      "4.1.1": 2461,
      "4.1.0": 4,
      "4.1.0-beta2": 0,
      "4.1.0-beta1": 0,
      "4.1.0-alpha3": 0,
      "4.1.0-alpha2": 0
    },
    {
      "date": "25/10/2021",
      "22.0.0-beta1": 0,
      "22.0.0-alpha9": 61,
      "22.0.0-alpha8": 1,
      "22.0.0-alpha7": 3,
      "22.0.0-alpha6": 69,
      "22.0.0-alpha5": 1,
      "22.0.0-alpha4": 0,
      "22.0.0-alpha3": 0,
      "22.0.0-alpha2": 0,
      "22.0.0-alpha10": 708,
      "22.0.0-alpha1": 0,
      "21.0.3": 997,
      "21.0.2": 395,
      "21.0.1": 193,
      "21.0.0": 119,
      "21.0.0-rc1": 4,
      "21.0.0-beta2": 35,
      "21.0.0-beta1": 1,
      "21.0.0-alpha9": 0,
      "21.0.0-alpha8": 0,
      "21.0.0-alpha7": 0,
      "21.0.0-alpha6": 0,
      "21.0.0-alpha5": 0,
      "21.0.0-alpha4": 0,
      "21.0.0-alpha3": 0,
      "21.0.0-alpha2": 0,
      "21.0.0-alpha13": 1,
      "21.0.0-alpha12": 0,
      "21.0.0-alpha11": 0,
      "21.0.0-alpha10": 0,
      "21.0.0-alpha1": 0,
      "21.0.0-alpha0.b163d3a8c": 0,
      "21.0.0-alpha0.29f1db3de": 0,
      "20.0.5": 184,
      "20.0.4": 27,
      "20.0.3": 126,
      "20.0.2": 122,
      "20.0.1": 29,
      "20.0.0": 128,
      "20.0.0-rc1": 0,
      "20.0.0-beta2": 0,
      "20.0.0-beta1": 0,
      "20.0.0-alpha6": 0,
      "20.0.0-alpha5": 0,
      "20.0.0-alpha4": 0,
      "20.0.0-alpha3": 0,
      "20.0.0-alpha2": 0,
      "20.0.0-alpha1": 0,
      "5.0.0-alpha1": 0,
      "4.3.0": 11836,
      "4.3.0-beta1": 0,
      "4.3.0-alpha1": 0,
      "4.2.0": 1644,
      "4.2.0-alpha1": 38,
      "4.1.1": 2629,
      "4.1.0": 4,
      "4.1.0-beta2": 0,
      "4.1.0-beta1": 0,
      "4.1.0-alpha3": 0,
      "4.1.0-alpha2": 0
    },
    {
      "date": "01/11/2021",
      "22.0.0-beta1": 40,
      "22.0.0-alpha9": 61,
      "22.0.0-alpha8": 2,
      "22.0.0-alpha7": 7,
      "22.0.0-alpha6": 43,
      "22.0.0-alpha5": 0,
      "22.0.0-alpha4": 0,
      "22.0.0-alpha3": 0,
      "22.0.0-alpha2": 0,
      "22.0.0-alpha10": 422,
      "22.0.0-alpha1": 1,
      "21.0.3": 1134,
      "21.0.2": 317,
      "21.0.1": 149,
      "21.0.0": 117,
      "21.0.0-rc1": 16,
      "21.0.0-beta2": 42,
      "21.0.0-beta1": 6,
      "21.0.0-alpha9": 1,
      "21.0.0-alpha8": 1,
      "21.0.0-alpha7": 1,
      "21.0.0-alpha6": 1,
      "21.0.0-alpha5": 1,
      "21.0.0-alpha4": 1,
      "21.0.0-alpha3": 1,
      "21.0.0-alpha2": 2,
      "21.0.0-alpha13": 1,
      "21.0.0-alpha12": 1,
      "21.0.0-alpha11": 1,
      "21.0.0-alpha10": 1,
      "21.0.0-alpha1": 1,
      "21.0.0-alpha0.b163d3a8c": 1,
      "21.0.0-alpha0.29f1db3de": 1,
      "20.0.5": 204,
      "20.0.4": 20,
      "20.0.3": 95,
      "20.0.2": 94,
      "20.0.1": 27,
      "20.0.0": 148,
      "20.0.0-rc1": 1,
      "20.0.0-beta2": 1,
      "20.0.0-beta1": 1,
      "20.0.0-alpha6": 1,
      "20.0.0-alpha5": 1,
      "20.0.0-alpha4": 1,
      "20.0.0-alpha3": 1,
      "20.0.0-alpha2": 1,
      "20.0.0-alpha1": 1,
      "5.0.0-alpha1": 1,
      "4.3.0": 11900,
      "4.3.0-beta1": 2,
      "4.3.0-alpha1": 1,
      "4.2.0": 1464,
      "4.2.0-alpha1": 42,
      "4.1.1": 2276,
      "4.1.0": 8,
      "4.1.0-beta2": 1,
      "4.1.0-beta1": 1,
      "4.1.0-alpha3": 1,
      "4.1.0-alpha2": 1
    },
    {
      "date": "08/11/2021",
      "22.0.0-beta1": 427,
      "22.0.0-alpha9": 3,
      "22.0.0-alpha8": 3,
      "22.0.0-alpha7": 5,
      "22.0.0-alpha6": 25,
      "22.0.0-alpha5": 1,
      "22.0.0-alpha4": 1,
      "22.0.0-alpha3": 2,
      "22.0.0-alpha2": 2,
      "22.0.0-alpha10": 166,
      "22.0.0-alpha1": 3,
      "21.0.3": 1490,
      "21.0.2": 313,
      "21.0.1": 174,
      "21.0.0": 106,
      "21.0.0-rc1": 6,
      "21.0.0-beta2": 38,
      "21.0.0-beta1": 15,
      "21.0.0-alpha9": 2,
      "21.0.0-alpha8": 2,
      "21.0.0-alpha7": 2,
      "21.0.0-alpha6": 2,
      "21.0.0-alpha5": 2,
      "21.0.0-alpha4": 2,
      "21.0.0-alpha3": 1,
      "21.0.0-alpha2": 7,
      "21.0.0-alpha13": 3,
      "21.0.0-alpha12": 2,
      "21.0.0-alpha11": 2,
      "21.0.0-alpha10": 2,
      "21.0.0-alpha0.29f1db3de": 1,
      "20.0.5": 225,
      "20.0.4": 31,
      "20.0.3": 94,
      "20.0.2": 74,
      "20.0.1": 20,
      "20.0.0": 140,
      "20.0.0-rc1": 1,
      "20.0.0-beta2": 1,
      "20.0.0-beta1": 1,
      "20.0.0-alpha5": 1,
      "20.0.0-alpha4": 1,
      "20.0.0-alpha2": 1,
      "4.3.0": 10330,
      "4.2.0": 1204,
      "4.2.0-alpha1": 43,
      "4.1.1": 1686,
      "4.1.0-beta1": 1,
      "4.1.0-alpha3": 1,
      "4.1.0-alpha2": 1
    }
  ]
}