{
  "downloads": {
    "2.4.0-alpha1": {
      "2021-2-4": 44
    },
    "2.4.1": {
      "2021-2-4": 174
    },
    "2.5.1": {
      "2021-2-4": 9
    },
    "2.5.0-alpha4": {
      "2021-2-4": 1
    },
    "2.4.2": {
      "2021-2-4": 317
    },
    "2.4.0": {
      "2021-2-4": 110
    },
    "2.5.2": {
      "2021-2-4": 8602
    },
    "2.2.1": {
      "2021-2-4": 3232
    },
    "2.5.0": {
      "2021-2-4": 126
    },
    "2.3.1": {
      "2021-2-4": 29
    },
    "2.4.4": {
      "2021-2-4": 95
    },
    "2.3.0": {
      "2021-2-4": 138
    },
    "2.4.3": {
      "2021-2-4": 438
    },
    "2.4.5": {
      "2021-2-4": 1532
    },
    "2.3.2": {
      "2021-2-4": 90
    },
    "2.1.0": {
      "2021-2-4": 5
    },
    "3.0.0-alpha1": {
      "2021-2-4": 8
    }
  }
}